{
    "swagger": "2.0",
    "info": {
        "description": "Simple Document Management System API",
        "title": "Document Management System API",
        "contact": {},
        "version": "1.0"
    },
    "host": "localhost:8080",
    "basePath": "/",
    "paths": {
        "/api/dashboard/stats": {
            "get": {
                "description": "Returns dashboard statistics including daily uploads and monthly active users",
                "produces": [
                    "application/json"
                ],
                "tags": [
                    "dashboard"
                ],
                "summary": "Get dashboard statistics",
                "responses": {
                    "200": {
                        "description": "OK",
                        "schema": {
                            "$ref": "#/definitions/models.Response"
                        }
                    }
                }
            }
        },
        "/api/dashboard/summary": {
            "get": {
                "description": "Returns dashboard summary with total users, sessions, files and storage",
                "produces": [
                    "application/json"
                ],
                "tags": [
                    "dashboard"
                ],
                "summary": "Get dashboard summary",
                "responses": {
                    "200": {
                        "description": "OK",
                        "schema": {
                            "$ref": "#/definitions/models.Response"
                        }
                    }
                }
            }
        },
        "/api/folders": {
            "get": {
                "description": "Returns the complete folder tree structure",
                "produces": [
                    "application/json"
                ],
                "tags": [
                    "folders"
                ],
                "summary": "Get folder tree structure",
                "responses": {
                    "200": {
                        "description": "OK",
                        "schema": {
                            "$ref": "#/definitions/models.Response"
                        }
                    }
                }
            }
        },
        "/api/folders/{id}": {
            "get": {
                "description": "Returns a specific folder and its children by ID",
                "produces": [
                    "application/json"
                ],
                "tags": [
                    "folders"
                ],
                "summary": "Get a specific folder",
                "parameters": [
                    {
                        "type": "string",
                        "description": "Folder ID",
                        "name": "id",
                        "in": "path",
                        "required": true
                    }
                ],
                "responses": {
                    "200": {
                        "description": "OK",
                        "schema": {
                            "$ref": "#/definitions/models.Response"
                        }
                    },
                    "404": {
                        "description": "Not Found",
                        "schema": {
                            "$ref": "#/definitions/models.Response"
                        }
                    }
                }
            }
        },
        "/api/history": {
            "get": {
                "description": "Returns all history scan records",
                "produces": [
                    "application/json"
                ],
                "tags": [
                    "history"
                ],
                "summary": "Get all history scan records",
                "responses": {
                    "200": {
                        "description": "OK",
                        "schema": {
                            "$ref": "#/definitions/models.Response"
                        }
                    }
                }
            },
            "post": {
                "description": "Creates a new scan record with machine name and barcode",
                "consumes": [
                    "application/json"
                ],
                "produces": [
                    "application/json"
                ],
                "tags": [
                    "history"
                ],
                "summary": "Create a new scan record",
                "parameters": [
                    {
                        "description": "Scan request",
                        "name": "request",
                        "in": "body",
                        "required": true,
                        "schema": {
                            "$ref": "#/definitions/models.ScanRequest"
                        }
                    }
                ],
                "responses": {
                    "201": {
                        "description": "Created",
                        "schema": {
                            "$ref": "#/definitions/models.Response"
                        }
                    },
                    "400": {
                        "description": "Bad Request",
                        "schema": {
                            "$ref": "#/definitions/models.Response"
                        }
                    }
                }
            }
        },
        "/api/history/{id}": {
            "get": {
                "description": "Returns a specific history scan record by ID",
                "produces": [
                    "application/json"
                ],
                "tags": [
                    "history"
                ],
                "summary": "Get a specific history scan record",
                "parameters": [
                    {
                        "type": "integer",
                        "description": "Scan ID",
                        "name": "id",
                        "in": "path",
                        "required": true
                    }
                ],
                "responses": {
                    "200": {
                        "description": "OK",
                        "schema": {
                            "$ref": "#/definitions/models.Response"
                        }
                    },
                    "400": {
                        "description": "Bad Request",
                        "schema": {
                            "$ref": "#/definitions/models.Response"
                        }
                    },
                    "404": {
                        "description": "Not Found",
                        "schema": {
                            "$ref": "#/definitions/models.Response"
                        }
                    }
                }
            },
            "delete": {
                "description": "Deletes a history scan record by ID",
                "produces": [
                    "application/json"
                ],
                "tags": [
                    "history"
                ],
                "summary": "Delete a history scan record",
                "parameters": [
                    {
                        "type": "integer",
                        "description": "Scan ID",
                        "name": "id",
                        "in": "path",
                        "required": true
                    }
                ],
                "responses": {
                    "200": {
                        "description": "OK",
                        "schema": {
                            "$ref": "#/definitions/models.Response"
                        }
                    },
                    "400": {
                        "description": "Bad Request",
                        "schema": {
                            "$ref": "#/definitions/models.Response"
                        }
                    },
                    "404": {
                        "description": "Not Found",
                        "schema": {
                            "$ref": "#/definitions/models.Response"
                        }
                    }
                }
            }
        },
        "/api/search": {
            "get": {
                "description": "Search through documents with optional filters",
                "produces": [
                    "application/json"
                ],
                "tags": [
                    "search"
                ],
                "summary": "Search documents",
                "parameters": [
                    {
                        "type": "string",
                        "description": "Search query",
                        "name": "q",
                        "in": "query"
                    },
                    {
                        "type": "boolean",
                        "description": "Filter by document name",
                        "name": "document",
                        "in": "query"
                    },
                    {
                        "type": "boolean",
                        "description": "Filter by tag",
                        "name": "tag",
                        "in": "query"
                    },
                    {
                        "type": "boolean",
                        "description": "Filter by content",
                        "name": "content",
                        "in": "query"
                    }
                ],
                "responses": {
                    "200": {
                        "description": "OK",
                        "schema": {
                            "$ref": "#/definitions/models.Response"
                        }
                    }
                }
            }
        },
        "/api/search/{id}": {
            "get": {
                "description": "Returns a specific document by document number",
                "produces": [
                    "application/json"
                ],
                "tags": [
                    "search"
                ],
                "summary": "Get a specific document",
                "parameters": [
                    {
                        "type": "string",
                        "description": "Document number",
                        "name": "id",
                        "in": "path",
                        "required": true
                    }
                ],
                "responses": {
                    "200": {
                        "description": "OK",
                        "schema": {
                            "$ref": "#/definitions/models.Response"
                        }
                    },
                    "404": {
                        "description": "Not Found",
                        "schema": {
                            "$ref": "#/definitions/models.Response"
                        }
                    }
                }
            }
        },
        "/api/upload": {
            "post": {
                "description": "Uploads a file and returns its metadata",
                "consumes": [
                    "multipart/form-data"
                ],
                "produces": [
                    "application/json"
                ],
                "tags": [
                    "upload"
                ],
                "summary": "Upload a single file",
                "parameters": [
                    {
                        "type": "file",
                        "description": "File to upload",
                        "name": "file",
                        "in": "formData",
                        "required": true
                    },
                    {
                        "type": "string",
                        "description": "Optional folder ID",
                        "name": "folderId",
                        "in": "formData"
                    }
                ],
                "responses": {
                    "200": {
                        "description": "OK",
                        "schema": {
                            "$ref": "#/definitions/models.Response"
                        }
                    },
                    "400": {
                        "description": "Bad Request",
                        "schema": {
                            "$ref": "#/definitions/models.Response"
                        }
                    },
                    "500": {
                        "description": "Internal Server Error",
                        "schema": {
                            "$ref": "#/definitions/models.Response"
                        }
                    }
                }
            }
        },
        "/api/upload/multiple": {
            "post": {
                "description": "Uploads multiple files in one request",
                "consumes": [
                    "multipart/form-data"
                ],
                "produces": [
                    "application/json"
                ],
                "tags": [
                    "upload"
                ],
                "summary": "Upload multiple files",
                "parameters": [
                    {
                        "type": "file",
                        "description": "Multiple files",
                        "name": "files",
                        "in": "formData",
                        "required": true
                    },
                    {
                        "type": "string",
                        "description": "Optional folder ID",
                        "name": "folderId",
                        "in": "formData"
                    }
                ],
                "responses": {
                    "200": {
                        "description": "OK",
                        "schema": {
                            "$ref": "#/definitions/models.Response"
                        }
                    },
                    "400": {
                        "description": "Bad Request",
                        "schema": {
                            "$ref": "#/definitions/models.Response"
                        }
                    },
                    "500": {
                        "description": "Internal Server Error",
                        "schema": {
                            "$ref": "#/definitions/models.Response"
                        }
                    }
                }
            }
        },
        "/api/upload/{filename}": {
            "delete": {
                "description": "Deletes a file by filename",
                "produces": [
                    "application/json"
                ],
                "tags": [
                    "upload"
                ],
                "summary": "Delete an uploaded file",
                "parameters": [
                    {
                        "type": "string",
                        "description": "Filename",
                        "name": "filename",
                        "in": "path",
                        "required": true
                    }
                ],
                "responses": {
                    "200": {
                        "description": "OK",
                        "schema": {
                            "$ref": "#/definitions/models.Response"
                        }
                    },
                    "400": {
                        "description": "Bad Request",
                        "schema": {
                            "$ref": "#/definitions/models.Response"
                        }
                    },
                    "404": {
                        "description": "Not Found",
                        "schema": {
                            "$ref": "#/definitions/models.Response"
                        }
                    },
                    "500": {
                        "description": "Internal Server Error",
                        "schema": {
                            "$ref": "#/definitions/models.Response"
                        }
                    }
                }
            }
        }
    },
    "definitions": {
        "models.Response": {
            "type": "object",
            "properties": {
                "data": {},
                "error": {
                    "type": "string"
                },
                "message": {
                    "type": "string"
                },
                "meta": {},
                "success": {
                    "type": "boolean"
                }
            }
        },
        "models.ScanRequest": {
            "type": "object",
            "properties": {
                "barcode": {
                    "type": "string"
                },
                "machine": {
                    "type": "string"
                }
            }
        }
    }
}